drytorch/__init__.py
drytorch/py.typed
drytorch/contrib/__init__.py
drytorch/contrib/optuna.py
drytorch/contrib/swa_utils.py
drytorch/contrib/torcheval.py
drytorch/contrib/torchmetrics.py
drytorch/core/__init__.py
drytorch/core/exceptions.py
drytorch/core/experiment.py
drytorch/core/log_events.py
drytorch/core/protocols.py
drytorch/core/register.py
drytorch/core/track.py
drytorch/lib/__init__.py
drytorch/lib/checkpoints.py
drytorch/lib/evaluations.py
drytorch/lib/gradient_ops.py
drytorch/lib/hooks.py
drytorch/lib/learn.py
drytorch/lib/load.py
drytorch/lib/models.py
drytorch/lib/objectives.py
drytorch/lib/runners.py
drytorch/lib/schedulers.py
drytorch/lib/train.py
drytorch/trackers/__init__.py
drytorch/trackers/base_classes.py
drytorch/trackers/csv.py
drytorch/trackers/hydra.py
drytorch/trackers/logging.py
drytorch/trackers/matplotlib.py
drytorch/trackers/plotly.py
drytorch/trackers/sqlalchemy.py
drytorch/trackers/tensorboard.py
drytorch/trackers/tqdm.py
drytorch/trackers/visdom.py
drytorch/trackers/wandb.py
drytorch/trackers/yaml.py
drytorch/utils/__init__.py
drytorch/utils/apply_ops.py
drytorch/utils/average.py
drytorch/utils/repr_utils.py
drytorch-0.1.0rc5.dist-info/METADATA
drytorch-0.1.0rc5.dist-info/WHEEL
drytorch-0.1.0rc5.dist-info/licenses/LICENSE
drytorch-0.1.0rc5.dist-info/RECORD
