Metadata-Version: 2.4
Name: drytorch
Version: 0.1.0rc5
Summary: This package helps train, document and evaluate a Pytorch model.
Project-URL: Repository, https://github.com/nverchev/drytorch
Project-URL: Issues, https://github.com/nverchev/drytorch/issues
Project-URL: Changelog, https://github.com/nverchev/drytorch/blob/master/CHANGELOG.md
Author-email: Nicolas Vercheval <nicolas.vercheval@ugent.be>
License: MIT License
License-File: LICENSE
Keywords: logger,pytorch
Classifier: License :: OSI Approved :: MIT License
Classifier: Operating System :: OS Independent
Classifier: Programming Language :: Python :: 3
Classifier: Programming Language :: Python :: 3.11
Classifier: Programming Language :: Python :: 3.12
Classifier: Programming Language :: Python :: 3.13
Classifier: Programming Language :: Python :: 3.14
Requires-Python: >=3.11
Requires-Dist: filelock>=3.12.0
Requires-Dist: numpy>=1.26.0
Requires-Dist: torch>=2.7.0
Requires-Dist: typing-extensions>=4.4.0
Provides-Extra: all-trackers
Requires-Dist: hydra-core>=1.3.0; extra == 'all-trackers'
Requires-Dist: ipython>=8.12.0; extra == 'all-trackers'
Requires-Dist: matplotlib>=3.3.0; extra == 'all-trackers'
Requires-Dist: omegaconf>=2.3.0; extra == 'all-trackers'
Requires-Dist: plotly>=4.10.0; extra == 'all-trackers'
Requires-Dist: pyyaml>=6.0; extra == 'all-trackers'
Requires-Dist: sqlalchemy>=2.0.12; extra == 'all-trackers'
Requires-Dist: tensorboard>=2.17.0; extra == 'all-trackers'
Requires-Dist: tqdm>=4.50.0; extra == 'all-trackers'
Requires-Dist: visdom>=0.1.6; extra == 'all-trackers'
Requires-Dist: wandb>=0.20.0; extra == 'all-trackers'
Provides-Extra: dev
Requires-Dist: hypothesis>=0.1.0; extra == 'dev'
Requires-Dist: jupytext>=1.18.1; extra == 'dev'
Requires-Dist: pre-commit>=4.3.0; extra == 'dev'
Requires-Dist: pytest-cov>=2.12.1; extra == 'dev'
Requires-Dist: pytest-mock>=3.4.0; extra == 'dev'
Requires-Dist: pytest>=8.0.0; extra == 'dev'
Provides-Extra: docs
Requires-Dist: myst-nb; extra == 'docs'
Requires-Dist: sphinx; extra == 'docs'
Requires-Dist: sphinx-rtd-theme; extra == 'docs'
Requires-Dist: sphinxcontrib-mermaid; extra == 'docs'
Provides-Extra: recommended
Requires-Dist: pyyaml>=6.0; extra == 'recommended'
Requires-Dist: tqdm>=4.50.0; extra == 'recommended'
Provides-Extra: support
Requires-Dist: ipywidgets; extra == 'support'
Requires-Dist: notebook; extra == 'support'
Requires-Dist: optuna>=4.0.0; extra == 'support'
Requires-Dist: pandas==2.3.0; extra == 'support'
Requires-Dist: pillow>=10.0.1; extra == 'support'
Requires-Dist: torcheval; extra == 'support'
Requires-Dist: torchmetrics>=1.0.0; extra == 'support'
Provides-Extra: type
Requires-Dist: basedpyright>=1.31.1; extra == 'type'
Requires-Dist: pandas-stubs; extra == 'type'
Requires-Dist: plotly-stubs; extra == 'type'
Requires-Dist: types-pyyaml; extra == 'type'
Requires-Dist: types-tqdm; extra == 'type'
